{
  "__collections__": {
   "products": {
      
 "1" : {
   "id": "1",
   "Item": "Fruits Combo",
   "Category": "fruits",
   "Caption": "Pack",
   "Description": "Mix de fruits en promo",
   "Comments":"0",
   "Likes" : "0",
   "Price": "15,000",
   "Image": "assets/img/products/fruit-combo.png"
 },
 "2" : {
   "id": "2",
   "Item": "Vegetables Combo",
   "Category": "vegetables",
   "Caption": "Pack",
   "Description": "Mix de legumes en promo",
   "Comments":"0",
   "Likes" : "0",
   "Price": "15,000",
   "Image": "assets/img/products/vegetable-combo.png"
 },
 "3" : {
   "id": "3",
   "Item": "African Egg Plants",
   "Category": "vegetables",
   "Caption": "1 Piece",
   "Description": "Aubergines (Ibibiringanya)",
   "Comments":"0",
   "Likes" : "0",
   "Price": "300",
   "Image": "assets/img/products/african-egg-plants.png"
 },
 "5" : {
   "id": "5",
   "Item": "Amaranthus",
   "Category": "vegetables",
   "Caption": "Bunch",
   "Description": "Amaranthes (Dodo)",
   "Comments":"0",
   "Likes" : "0",
   "Price": "300",
   "Image": "assets/img/products/amaranthus.png"
 },
 "6" : {
   "id": "6",
   "Item": "Thyme",
   "Category": "vegetables",
   "Caption": "Bunch",
   "Description": "Thym (Te)",
   "Comments":"0",
   "Likes" : "0",
   "Price": "300",
   "Image": "assets/img/products/thyme.png"

 },
 "19" : {
   "id": "19",
   "Item": "Carrots",
   "Category": "vegetables",
   "Caption": "1 kg",
   "Description": "Carottes (Karoti)",
   "Comments":"0",
   "Likes" : "0",
   "Price": "900",
   "Image": "assets/img/products/carrots.png"
 },
 "48" : {
   "id": "48",
   "Item": "Onions (Red)",
   "Category": "vegetables",
   "Caption": "1 kg",
   "Description": "Oignons Rouges (Ibitunguru by'Umutuku) - Local",
   "Comments":"0",
   "Likes" : "0",
   "Price": "1,000",
   "Image": "assets/img/products/red-onions.png"
 },
 "7" : {
   "id": "7",
   "Item": "Passion Fruits",
   "Category": "fruits",
   "Caption": "1 kg",
   "Description": "Maracuja (Amatunda)",
   "Comments":"0",
   "Likes" : "0",
   "Price": "1,500",
   "Image": "assets/img/products/passion-fruits.png"
 },
 "8" : {
   "id": "8",
   "Item": "Pineapples",
   "Category": "fruits",
   "Caption": "1 Piece",
   "Description": "Ananas (Inanasi)",
   "Comments":"0",
   "Likes" : "0",
   "Price": "1,200",
   "Image": "assets/img/products/pineapples.png"
 },
 "9" : {
   "id": "9",
   "Item": "Raspberries",
   "Category": "fruits",
   "Caption": "500g",
   "Description": "Fruits",
   "Comments":"0",
   "Likes" : "0",
   "Price": "22,000",
   "Image": "assets/img/products/raspberries.png"
 },
 "10" : {
   "id": "10",
   "Item": "Baking Powder",
   "Category": "foods",
   "Caption": "Sac",
   "Description": "Levure",
   "Comments":"0",
   "Likes" : "0",
   "Price": "300",
   "Image": "assets/img/products/baking-powder.png"
 },
 "11" : {
   "id": "11",
   "Item": "Black Tea",
   "Category": "foods",
   "Caption": "Pack",
   "Description": "Black Tea (SORWATHE Light)",
   "Comments":"0",
   "Likes" : "0",
   "Price": "2,300",
   "Image": "assets/img/products/black-tea.png"
 },
 "12" : {
   "id": "12",
   "Item": "Brown Sugar",
   "Category": "foods",
   "Caption": "1 kg",
   "Description": "Sucre Brun (Isukari)",
   "Comments":"0",
   "Likes" : "0",
   "Price": "1,200",
   "Image": "assets/img/products/brown-sugar.png"
 },
 "13" : {
   "id": "13",
   "Item": "Feta Cheese",
   "Category": "foods",
   "Caption": "1 Piece",
   "Description": "Formage Feta",
   "Comments":"0",
   "Likes" : "0",
   "Price": "5,000",
   "Image": "assets/img/products/feta-cheese.png"
 },
 "14" : {
   "id": "14",
   "Item": "Toothpaste (Colgate)",
   "Category": "care",
   "Caption": "1 Piece",
   "Description": "Dentifrice pour adulte (Colgate)",
   "Comments":"0",
   "Likes" : "0",
   "Price": "1,300",
   "Image": "assets/img/products/toothpaste.png"
 },
 "15" : {
   "Item": "Air Freshener",
   "Category": "care",
   "Caption": "Bottle",
   "Description": "Désodorisant  (Tropical)",
   "Comments":"0",
   "Likes" : "0",
   "Price": "2,500",
   "Image": "assets/img/products/air-freshener.png"
 },
 "16" : {
   "id": "16",
   "Item": "Dish Washing Liquid",
   "Category": "care",
   "Caption": "Bottle",
   "Description": "Savon Vaisselle (Simba)",
   "Comments":"0",
   "Likes" : "0",
   "Price": "1,600",
   "Image": "assets/img/products/dish-washing-liquid.png"
 },
 "17" : {
   "id": "17",
   "Item": "Kitchen Towel",
   "Category": "care",
   "Caption": "Bottle",
   "Description": "Torchon Essuie-Vaisselle",
   "Comments":"0",
   "Likes" : "0",
   "Price": "3,500",
   "Image": "assets/img/products/kitchen-towel.png"
 }

   }
}
}